receipt_generator/__init__.py
receipt_generator/__main__.py
receipt_generator/generator.py
receipt_generator_NovEf-0.1.dist-info/METADATA
receipt_generator_NovEf-0.1.dist-info/WHEEL
receipt_generator_NovEf-0.1.dist-info/top_level.txt
receipt_generator_NovEf-0.1.dist-info/RECORD
